rest_apiresponse/__init__.py
rest_apiresponse/apiresponse.py
stark-rest-apiresponse/__init__.py
stark-rest-apiresponse/stark-rest-apiresponse.py
stark_rest_apiresponse-0.0.4.dist-info/LICENCE.txt
stark_rest_apiresponse-0.0.4.dist-info/METADATA
stark_rest_apiresponse-0.0.4.dist-info/WHEEL
stark_rest_apiresponse-0.0.4.dist-info/top_level.txt
stark_rest_apiresponse-0.0.4.dist-info/RECORD
