Metadata-Version: 2.1
Name: stark-rest-apiresponse
Version: 0.0.4
Summary: Easy way to get the standard rest api response
Home-page: UNKNOWN
Author: Stark Digital Media Services Pvt. Ltd.
Author-email: starkengg81@gmail.com
License: UNKNOWN
Keywords: stark,rest-api,rest-api-response,stark-rest-apiresponse
Platform: UNKNOWN
Classifier: Operating System :: OS Independent
Classifier: License :: OSI Approved :: MIT License
Classifier: Programming Language :: Python :: 3
Requires-Python: >=3.6
License-File: LICENCE.txt
